README.rst
setup.py
libtivomind/__init__.py
libtivomind/api.py
libtivomind/rpc.py
libtivomind.egg-info/PKG-INFO
libtivomind.egg-info/SOURCES.txt
libtivomind.egg-info/dependency_links.txt
libtivomind.egg-info/top_level.txt
libtivomind.egg-info/zip-safe